{"created_at": "Mon Mar 15 02:14:48 +0000 2021", "id": 1371283711606595590, "text": " A PROP SITO DE DIFERENCIA DE FALLECIDOS POR COVID ", "user": {"id": 292409067, "name": "Luis Humberto Montero", "location": null, "description": "Humanista", "followers_count": 444, "friends_count": 1070, "listed_count": 0, "favourites_count": 42816, "statuses_count": 9006, "created_at": "Tue May 03 16:11:01 +0000 2011", "time_zone": null, "lang": null}, "entities": {"hashtags": [], "user_mentions": []}, "timestamp_ms": "1615774488723"}