{"created_at": "Mon Mar 15 02:14:48 +0000 2021", "id": 1371283710733996035, "text": " KamalaHarris POTUS WhiteHouse SenateDems", "user": {"id": 1160200911299366912, "name": "genereaux2019", "location": null, "description": "We are fighting for the soul of our nation. Time for patriots to suit up & show up. #DefendDemocracy #RuleOfLaw \ud83c\uddfa\ud83c\uddf8\u2764\ufe0f\ud83c\uddfa\ud83c\uddf8", "followers_count": 535, "friends_count": 768, "listed_count": 2, "favourites_count": 94090, "statuses_count": 94147, "created_at": "Sat Aug 10 14:47:07 +0000 2019", "time_zone": null, "lang": null}, "entities": {"hashtags": [], "user_mentions": [{"screen_name": "KamalaHarris", "name": "Kamala Harris", "id": 30354991, "id_str": "30354991", "indices": [0, 13]}, {"screen_name": "POTUS", "name": "President Biden", "id": 1349149096909668363, "id_str": "1349149096909668363", "indices": [14, 20]}, {"screen_name": "WhiteHouse", "name": "The White House", "id": 1323730225067339784, "id_str": "1323730225067339784", "indices": [21, 32]}, {"screen_name": "SenateDems", "name": "Senate Democrats", "id": 73238146, "id_str": "73238146", "indices": [33, 44]}]}, "timestamp_ms": "1615774488515"}